memory.v
module memory (
    input clk,
    input mem_read,
    input mem_write,
    input [7:0] address,
    input [7:0] data_in,
    output reg [7:0] mem_data
    );
    reg [7:0] mem [0:255]; // 256 Byte memory
    always @(posedge clk) begin
        if (mem_read)
            mem_data <= mem[address];
        if (mem_write)
            mem[address] <= data_in;
    end
endmodule

control_unit.v
module control_unit (
    input clk,
    input reset,
    input [7:0] opcode,
    output reg load_ac, load_mq, load_pc, load_ir,
    output reg mem_read, mem_write,
    output reg increment_pc, // PC artırma sinyali
    output reg add_enable // Toplama işlemi için sinyal
    // output reg store_enable  // AC'deki veriyi belleğe yazma sinyali
);
    // Durum tanımları
    parameter FETCH = 2'b00, DECODE = 2'b01, EXECUTE = 2'b10, WRITE_BACK = 2'b11;
    reg [1:0] state;
    reg [7:0] ir_reg;  // IR kayıt için ekledim

    always @(posedge clk or posedge reset) begin
        if (reset) begin
            load_ac <= 0; load_mq <= 0; load_pc <= 0; load_ir <= 0;
            mem_read <= 0; mem_write <= 0; increment_pc <= 0; add_enable <= 0; 
            // store_enable <= 0;
            state <= FETCH;
            // Tüm sinyalleri sıfırla
            
            ir_reg <= 0;
            //$display("log 2 : control_unit reset success - State: %b",state); // İşlemden önce opcode ve state");
        end else begin
            //$display("Log 3 : (after else begin) Opcode: %d, State: %b", opcode, state);
            case (state)
                FETCH: begin
                    mem_read <= 1;     // Bellekten komut oku
                    load_ir <= 1;      // IR'ye yükle
                    increment_pc <= 1; // PC'yi artır
                    state <= DECODE;   // Sonraki durum
                    //$display("log 4: fetch bitti - State: %b",state); // İşlemden önce opcode ve state
                end
                DECODE: begin
                    // Fetch aşamasını bitir
                    mem_read <= 0;
                    load_ir <= 0;
                    increment_pc <= 0;
                    ir_reg <= opcode; // Opcode IR'ye yüklendi
                    state <= EXECUTE; // Opcode'u işle
                    //$display("Log 5 : Decode bitti - State: %b",state); // İşlemden önce opcode ve state
                end
                    EXECUTE: begin
                    //$display("Log 6 : Opcode: %d, State: %b, Before Operation", opcode, state); // İşlemden önce opcode ve state
                    case (opcode)
                        8'd1: begin // Load
                            //$display("Log 7 : Opcode: %d, State: %b, Operation: Load start", opcode, state); // Burada işlemi de yazdırıyoruz
                            mem_read <= 1;  // Bellekten okuma işlemi başlat
                            load_ac <= 1;   // AC'yi yükle
                            //$display("Log 8 : Opcode: %d, State: %b, Operation: Load end / mem_read: %d , load_ac: %d  ", opcode, state, mem_read, load_ac); // Burada işlemi de yazdırıyoruz
                        end
                        8'd2: begin // Store
                            //$display("Log 9 : Opcode: %d, State: %b, Operation: Store", opcode, state);
                            mem_write <= 1;  // Belleğe yazma işlemi başlat
                            // store_enable <= 1; 
                        end
                        8'd3: begin // Add
                            //$display("Log 10 : Opcode: %d, State: %b, Operation: Add start", opcode, state);
                            mem_read <= 1;   // Bellekten veri oku
                            add_enable <= 1; // Toplama işlemini başlat
                        end

                        8'd4: begin // Sub
                            //$display("Log 12 : Opcode: %d, State: %b, Operation: Sub start", opcode, state);
                            mem_read <= 1;   // Bellekten veri oku
                            load_ac <= 1;    // Çıkarma sonucu AC'ye yazılacak
                        end
                        8'd5: begin // Jump
                            //$display("Log 13 : Opcode: %d, State: %b, Operation: Jump", opcode, state);
                            load_pc <= 1;   // PC'yi yükle
                            increment_pc <= 0; // Jump sırasında PC artırılmaz
                        end
                        default: ; // No operation
                    endcase
                    //$display("After Operation: mem_read: %b, load_ac: %b", mem_read, load_ac); // Debugging the signals
                    state <= WRITE_BACK;
                end

                WRITE_BACK: begin
                    // Tüm sinyalleri sıfırla ve FETCH'e dön
                    load_ac <= 0; load_mq <= 0; load_pc <= 0; load_ir <= 0;
                    mem_read <= 0; mem_write <= 0; increment_pc <= 0; add_enable <= 0; 
                    // store_enable <= 0;
                    state <= FETCH;
                end
            endcase
        end
    end
endmodule

IR.v
module IR (
    input clk,
    input reset,
    input load_ir,
    input [7:0] mem_data,
    output reg [7:0] ir_data
    );
    always @(posedge clk or posedge reset) begin
        if (reset)
            ir_data <= 8'd0;
        else if (load_ir)
            ir_data <= mem_data;
    end
endmodule

PC.v
module PC (
    input clk,
    input reset,
    input load_pc,
    input increment_pc, // Yeni: PC'yi bir artırmak için sinyal
    input [7:0] address,
    output reg [7:0] pc_data
    );

    always @(posedge clk or posedge reset) begin
        if (reset)
            pc_data <= 8'd0; // Reset durumunda PC sıfırlanır
        else if (load_pc)
            pc_data <= address; // Harici bir değer yüklenir
        else if (increment_pc)
            pc_data <= pc_data + 8'd1; // PC bir artırılır
            //PC nin pc_data ile çıkardığı sonucu bir artırır.
    end
endmodule

MQ.v
module MQ (
    input clk,
    input reset,
    input load_mq,
    input [7:0] mem_data,
    output reg [7:0] mq_data
    );
        always @(posedge clk or posedge reset) begin
            if (reset)
                mq_data <= 8'd0;
            else if (load_mq)
                mq_data <= mem_data;
    end
endmodule

AC.v
module AC (
    input clk,
    input reset,
    input load_ac,
    input add_enable, // Bellekteki değeri AC'ye eklemek için
    input [7:0] mem_data,
    output reg [7:0] ac_data
    // output reg [7:0] ac_to_mem  // Belleğe yazılacak veri
);
    always @(posedge clk or posedge reset) begin
    if (reset) begin
        ac_data <= 8'd0; // Reset durumunda AC sıfırlanır
    end else if (load_ac) begin
        ac_data <= mem_data; // Bellekten alınan değer AC'ye yüklenir
    end else if (add_enable) begin
        //$display("AC toplama icerisi ac_data: %d, Mem: %d", ac_data, mem_data);
        ac_data <= ac_data + mem_data; // Bellekten alınan değer AC'ye eklenir
        //$display("AC toplama sonu ac_data: %d, Mem: %d", ac_data, mem_data);
        // ac_to_mem <= ac_data; // Belleğe yazılacak veri
    end
end

endmodule

IAS.v
module IAS (
    input clk,
    input reset,
    input [7:0] opcode,
    input [7:0] address,
    input [7:0] data_in,
    output [7:0] data_out
);
    wire load_ac, load_mq, load_pc, load_ir;
    wire mem_read, mem_write, increment_pc;
    wire [7:0] ac_data, mq_data, pc_data, ir_data, mem_data;
    wire add_enable;

    // Modülleri bağla
    AC ac(clk, reset, load_ac, add_enable,  mem_data, ac_data);
    MQ mq(clk, reset, load_mq, mem_data, mq_data);
    PC pc(clk, reset, load_pc, increment_pc, address, pc_data);
    IR ir(clk, reset, load_ir, mem_data, ir_data);
    // control_unit cu(clk, reset, opcode, load_ac, load_mq, load_pc, load_ir, mem_read, mem_write, increment_pc, add_enable, store_enable);
    control_unit cu(clk, reset, opcode, load_ac, load_mq, load_pc, load_ir, mem_read, mem_write, increment_pc, add_enable);


    // memory mem(
    //     .clk, 
    //     .mem_read, 
    //     .mem_write, 
    //     .address,   
    //     .data_in(store_enable ? ac_data : 8'b0),  
    //     .mem_data);

    memory mem(clk, mem_read, mem_write, address, data_in, mem_data);

    // memory mem(
    //     .clk(clk), 
    //     .mem_read(mem_read), 
    //     .mem_write(mem_write), 
    //     .address(address), 
    //     .data_in(store_enable ? ac_data : data_in), 
    //     .mem_data(mem_data)
    // );

    // Çıkış
    assign data_out = ac_data; // Örneğin, sonuç AC üzerinden verilir
    //assign data_in = ac_data; // Örneğin, sonuç AC üzerinden verilir

    // assign data_in = (load_ac) ? ac_data :
    //              (load_mq) ? mq_data :
    //              (load_pc) ? pc_data :
    //              (load_ir) ? ir_data : 8'b0;
endmodule

testbench.v
module testbench;
    reg clk, reset;
    reg [7:0] opcode, address, data_in;
    wire [7:0] data_out;

    // IAS modülünü instantiate et
    IAS ias(
        .clk(clk),
        .reset(reset),
        .opcode(opcode),
        .address(address),
        .data_in(data_in),
        .data_out(data_out)
    );

    // Clock sinyali oluştur
    always begin
        #5 clk = ~clk;  // Saat sinyali her 5 birimde bir tersine döner
    end
    
    initial begin
        // Dump dosyasını oluştur
        $dumpfile("simulation.vcd");
        $dumpvars(0, testbench);


        
        // İlk ayarlar
        clk = 0;
        reset = 1;
        opcode = 8'd0;
        address = 8'd0;
        data_in = 8'd0;

        // Reset işlemi
        #10 reset = 0;
        $display("Reset işlemi tamamlandı.");

        // Monitor ile izlenecek sinyalleri ekleyin
        // $monitor("Time: %0t | opcode: %d | address: %d | data_in: %d | mem_write: %d | mem_read: %d | AC: %d | data_out: %d | ias.mem.mem[11]: %d | ias.mem.mem[12]: %d | ias.mem.mem[13]: %d | add_enable: %d | load_ac: %d | load_mq: %d | load_pc: %d | load_ir: %d", 
        //         $time, opcode, address, data_in, ias.mem.mem_write, ias.mem.mem_read, ias.ac.ac_data, data_out, ias.mem.mem[11], ias.mem.mem[12], ias.mem.mem[13], ias.ac.add_enable, ias.cu.load_ac, ias.cu.load_mq, ias.cu.load_pc, ias.cu.load_ir);

        
        // Test 1: Belleğe veri yazma (manüel yükleme)
        
        // Belleğe veri yazma (manüel yükleme)
        $display("TEST 1 : Load testi");
        $display("Load testi");
        $display("Bellege veri yukleniyor...");
        ias.mem.mem[1] = 8'd150; // Belleğin 1. adresine 150 değerini yükle
        #10;
        // Load işlemi
        $display("Load islemi basliyor...");
        opcode = 8'd1; // Load komutu
        address = 8'd1; // 1. adresteki veriyi yükle

        #30; // FETCH, DECODE ve EXECUTE için yeterli süre bekle
        $display("AC degeri kontrol ediliyor...");
        $display("Beklenen AC Degeri: 150, Gercek AC Degeri: %d", data_out);

        // Test sonucu değerlendirme
        if (data_out == 8'd150) begin
            $display("Test Basarili: Bellekten dogru veri yüklendi.");
        end else begin
            $display("Test Basarisiz: Beklenen deger 150, ancak %d alindi.", data_out);
        end
        


        

        // İlk ayarlar
        clk = 0;
        reset = 1;
        opcode = 8'd0;
        address = 8'd0;
        data_in = 8'd0;

        // Reset işlemi
        #10 reset = 0;


        $display("------------------------");
        // Test 2: Store İşlemi
        // 1. Belleğe veri yükle
        $display("TEST 2 : Store testi");
        $display("Store testi");
        $display("Bellege veri yukleniyor...");
        address = 8'd1;       // Belleğin 1. adresine veri yazılacak
        data_in = 8'd123;     // Yazılacak veri 123
        opcode = 8'd1;        // Load komutu (örnek)
        #20;                  // FETCH, DECODE, EXECUTE işlemleri için bekle

        // 2. Load edilen veriyi AC'ye yaz
        $display("AC'ye veri yükleniyor...");
        #20;                  // Load işleminin bitmesini bekle

        // 3. Store komutunu çalıştır
        $display("Store islemi basliyor...");
        opcode = 8'd2;        // Store komutu
        address = 8'd2;       // AC'deki veri, 2. adrese yazılacak
        #40;                  // FETCH, DECODE, EXECUTE ve WRITE_BACK işlemleri için bekle

        // 4. Store işlemini kontrol et
        $display("Store islemi kontrol ediliyor...");
        $display("Beklenen Bellek [2] Degeri: 123, Gercek Deger: %d", ias.mem.mem[2]);
        
        //$monitor("Time: %0t | opcode: %d | address: %d | data_in: %d | mem_write: %d | mem_read: %d | AC: %d | Mem[2]: %d", 
        //$time, opcode, address, data_in, ias.mem.mem_write, ias.mem.mem_read, ias.ac.ac_data, ias.mem.mem[2]);

        if (ias.mem.mem[2] == 8'd123) begin
            $display("Test Basarili: Dogru deger bellege yazildi.");
        end else begin
            $display("Test Basarisiz: Beklenen deger 123, ancak %d alindi.", ias.mem.mem[2]);
        end
        
        
        $display("------------------------");

        
        // İlk ayarlar
        clk = 0;
        reset = 1;
        opcode = 8'd0;
        address = 8'd0;
        data_in = 8'd0;

        // Reset işlemi
        #10 reset = 0;
        

        // Test 3: ADD işlemi
        //Testte 25 ve 50 değerlerini toplayıp 75 değerini elde etmeye çalışıyoruz.
        $display("TEST 3 : ADD testi.");
        $display("ADD testi.");
        // Belleğe 1. değeri yaz
        $display("Belleğe veri yazılıyor...");
        address = 8'd11;
        data_in = 8'd25; // İlk değer
        opcode = 8'd2; // STORE komutu
        #40;

        // Belleğe 2. değeri yaz
        address = 8'd12;
        data_in = 8'd50; // İkinci değer
        opcode = 8'd2; // STORE komutu
        #40;

        // İlk değeri AC'ye yükle (LOAD işlemi)
        $display("AC'ye veri yükleniyor...");
        opcode = 8'd1; // LOAD komutu
        address = 8'd11;
        #40;

        // İkinci değeri AC ile topla (ADD işlemi)
        $display("AC ile veri toplanıyor...");
        opcode = 8'd3; // ADD komutu
        address = 8'd12;
        #40;        //en az 30 gerekiyor.

    

        // // Sonucu bellek 3'e yaz (STORE işlemi)
        // $display("Sonuç bellek 3'e yazılıyor...");
        // opcode = 8'd2; // STORE komutu
        // address = 8'd3; // Bellek 3'e yazılacak
        // #40;

        // AC'den belleğe yazma (STORE_AC)
        $display("AC'deki veri belleğe yazılıyor...");
        opcode = 8'd6;  // Yeni STORE_AC opcode
        address = 8'd13; // Bellek adresi
        #40; // Verilerin yazılması için bekle


        // Sonuç kontrolü: Bellek 3'ün verisini kontrol et
        $display("Sonuc Kontrolu...");
        $display("Bellek[13] Beklenen Degeri: 75, Gercek Degeri: %d", ias.mem.mem[13]);

        if (ias.mem.mem[13] == 8'd75) begin
            $display("Test Basarili: Bellek[13]'e dogru deger yazildi.");
        end else begin
            $display("Test Başarısız: Beklenen değer 75, ancak %d alındı.", ias.mem.mem[13]);
        end

        $display("------------------------");

        // Jump komutunu test et
        $display("TEST 4 : JUMP testi");
        $display("PC'ye atama yapılıyor...");

        // İlk ayarlar
        clk = 0;
        reset = 1;
        opcode = 8'd0;
        address = 8'd0;
        data_in = 8'd0;

        // Reset işlemi
        #10 reset = 0;

        // Test için başlangıç durumu
        ias.cu.load_pc = 0;      // PC başlangıçta yüklenmiyor
        ias.mem.mem[20] = 8'd10; // Jump adresini belleğe yazıyoruz
        address = 8'd20;         // Jump adresi
        opcode = 8'd5;           // Jump komutu (Opcode: 5)

        // Jump işlemi başlıyor
        $display("Jump islemi basliyor...");
        #40; // FETCH, DECODE, EXECUTE ve WRITE_BACK için yeterli süre bekle

        // Jump sonrası PC değerini kontrol et
        $display("Jump sonrasi PC kontrol ediliyor...");
        $display("Beklenen PC degeri: 20, Gercek PC degeri: %d", ias.pc.pc_data);

        if (ias.pc.pc_data == 8'd20) begin
            $display("Test Basarili: Jump komutu dogru calisti.");
        end else begin
            $display("Test Basarisiz: Beklenen PC degeri 20, ancak %d alindi.", ias.pc.pc_data);
        end

        $display("------------------------");



        // Simülasyonu bitir
        #10;
        $finish;
    end

endmodule

simulation.vcd
$date
	Mon Jan 13 01:44:36 2025
$end
$version
	Icarus Verilog
$end
$timescale
	1s
$end
$scope module testbench $end
$var wire 8 ! data_out [7:0] $end
$var reg 8 " address [7:0] $end
$var reg 1 # clk $end
$var reg 8 $ data_in [7:0] $end
$var reg 8 % opcode [7:0] $end
$var reg 1 & reset $end
$scope module ias $end
$var wire 8 ' ac_data [7:0] $end
$var wire 1 ( add_enable $end
$var wire 8 ) address [7:0] $end
$var wire 1 * clk $end
$var wire 8 + data_in [7:0] $end
$var wire 8 , data_out [7:0] $end
$var wire 1 - increment_pc $end
$var wire 8 . ir_data [7:0] $end
$var wire 1 / load_ac $end
$var wire 1 0 load_ir $end
$var wire 1 1 load_mq $end
$var wire 1 2 load_pc $end
$var wire 8 3 mem_data [7:0] $end
$var wire 1 4 mem_read $end
$var wire 1 5 mem_write $end
$var wire 8 6 mq_data [7:0] $end
$var wire 8 7 opcode [7:0] $end
$var wire 8 8 pc_data [7:0] $end
$var wire 1 9 reset $end
$scope module ac $end
$var wire 1 ( add_enable $end
$var wire 1 * clk $end
$var wire 1 / load_ac $end
$var wire 8 : mem_data [7:0] $end
$var wire 1 9 reset $end
$var reg 8 ; ac_data [7:0] $end
$upscope $end
$scope module mq $end
$var wire 1 * clk $end
$var wire 1 1 load_mq $end
$var wire 8 < mem_data [7:0] $end
$var wire 1 9 reset $end
$var reg 8 = mq_data [7:0] $end
$upscope $end
$scope module pc $end
$var wire 8 > address [7:0] $end
$var wire 1 * clk $end
$var wire 1 - increment_pc $end
$var wire 1 2 load_pc $end
$var wire 1 9 reset $end
$var reg 8 ? pc_data [7:0] $end
$upscope $end
$scope module ir $end
$var wire 1 * clk $end
$var wire 1 0 load_ir $end
$var wire 8 @ mem_data [7:0] $end
$var wire 1 9 reset $end
$var reg 8 A ir_data [7:0] $end
$upscope $end
$scope module cu $end
$var wire 1 * clk $end
$var wire 8 B opcode [7:0] $end
$var wire 1 9 reset $end
$var reg 1 C add_enable $end
$var reg 1 D increment_pc $end
$var reg 8 E ir_reg [7:0] $end
$var reg 1 F load_ac $end
$var reg 1 G load_ir $end
$var reg 1 H load_mq $end
$var reg 1 I load_pc $end
$var reg 1 J mem_read $end
$var reg 1 K mem_write $end
$var reg 2 L state [1:0] $end
$upscope $end
$scope module mem $end
$var wire 8 M address [7:0] $end
$var wire 1 * clk $end
$var wire 8 N data_in [7:0] $end
$var wire 1 4 mem_read $end
$var wire 1 5 mem_write $end
$var reg 8 O mem_data [7:0] $end
$upscope $end
$upscope $end
$upscope $end
$enddefinitions $end
#0
$dumpvars
bx O
b0 N
b0 M
b0 L
0K
0J
0I
0H
0G
0F
b0 E
0D
0C
b0 B
b0 A
bx @
b0 ?
b0 >
b0 =
bx <
b0 ;
bx :
19
b0 8
b0 7
b0 6
05
04
bx 3
02
01
00
0/
b0 .
0-
b0 ,
b0 +
0*
b0 )
0(
b0 '
1&
b0 %
b0 $
0#
b0 "
b0 !
$end
#5
1#
1*
#10
0#
0*
b10 %
b10 7
b10 B
b11001 $
b11001 +
b11001 N
b1 "
b1 )
b1 >
b1 M
0&
09
#15
b1 L
1D
1-
1G
10
1J
14
1#
1*
#20
0#
0*
#25
b10 L
b10 E
0D
0-
0G
00
0J
04
bx A
bx .
b1 ?
b1 8
1#
1*
#30
0#
0*
#35
b11 L
1K
15
1#
1*
#40
0#
0*
#45
b0 L
0K
05
1#
1*
#50
0#
0*
b110010 $
b110010 +
b110010 N
b10 "
b10 )
b10 >
b10 M
#55
b1 L
1D
1-
1G
10
1J
14
1#
1*
#60
0#
0*
#65
b10 L
0D
0-
0G
00
0J
04
b10 ?
b10 8
1#
1*
#70
0#
0*
#75
b11 L
1K
15
1#
1*
#80
0#
0*
#85
b0 L
0K
05
1#
1*
#90
0#
0*
b1 "
b1 )
b1 >
b1 M
b1 %
b1 7
b1 B
#95
b1 L
1D
1-
1G
10
1J
14
1#
1*
#100
0#
0*
#105
b11001 O
b11001 3
b11001 :
b11001 <
b11001 @
b10 L
b1 E
0D
0-
0G
00
0J
04
b11 ?
b11 8
1#
1*
#110
0#
0*
#115
b11 L
1F
1/
1J
14
1#
1*
#120
0#
0*
#125
b0 L
0J
04
0F
0/
b11001 ;
b11001 '
b11001 !
b11001 ,
1#
1*
#130
0#
0*
b10 "
b10 )
b10 >
b10 M
b11 %
b11 7
b11 B
#135
b1 L
1D
1-
1G
10
1J
14
1#
1*
#140
0#
0*
#145
b110010 O
b110010 3
b110010 :
b110010 <
b110010 @
b10 L
b11 E
0D
0-
0G
00
0J
04
b11001 A
b11001 .
b100 ?
b100 8
1#
1*
#150
0#
0*
#155
b11 L
1C
1(
1J
14
1#
1*
#160
0#
0*
#165
b0 L
0C
0(
0J
04
b1001011 ;
b1001011 '
b1001011 !
b1001011 ,
1#
1*
#170
0#
0*
b11 "
b11 )
b11 >
b11 M
b10 %
b10 7
b10 B
#175
b1 L
1D
1-
1G
10
1J
14
1#
1*
#180
0#
0*
#185
bx O
bx 3
bx :
bx <
bx @
b10 L
b10 E
0D
0-
0G
00
0J
04
b110010 A
b110010 .
b101 ?
b101 8
1#
1*
#190
0#
0*
#195
b11 L
1K
15
1#
1*
#200
0#
0*
#205
b0 L
0K
05
1#
1*
#210
0#
0*
#215
b1 L
1D
1-
1G
10
1J
14
1#
1*
